setup.py
jikan_sqlalchemy_utils/__init__.py
jikan_sqlalchemy_utils/merge_args.py
jikan_sqlalchemy_utils/ocolumn.py
jikan_sqlalchemy_utils/query.py
jikan_sqlalchemy_utils/sau_fixed.py
jikan_sqlalchemy_utils/session.py
jikan_sqlalchemy_utils/sqlalchemy_pysqlite_fixup.py
jikan_sqlalchemy_utils/table.py
jikan_sqlalchemy_utils.egg-info/PKG-INFO
jikan_sqlalchemy_utils.egg-info/SOURCES.txt
jikan_sqlalchemy_utils.egg-info/dependency_links.txt
jikan_sqlalchemy_utils.egg-info/requires.txt
jikan_sqlalchemy_utils.egg-info/top_level.txt