Metadata-Version: 1.1
Name: jikan-sqlalchemy-utils
Version: 1.0.0
Summary: jikan sqlalchemy utilities
Home-page: https://hydra.ecd.space/jikan/jikan_sqlalchemy_utils/
Author: jikan@cock.li
Author-email: jikan@cock.li
License: LGPLv3
Platform: UNKNOWN
Classifier: Programming Language :: Python :: 3 :: Only
